CHANGELOG.md
terraform_linter_tool/__init__.py
terraform_linter_tool/ai_assist/__init__.py
terraform_linter_tool/ai_assist/issue_handler.py
terraform_linter_tool/config.py
terraform_linter_tool/lint_factory.py
terraform_linter_tool/linter_runner.py
terraform_linter_tool/linters/__init__.py
terraform_linter_tool/linters/base_linter.py
terraform_linter_tool/linters/checkov.py
terraform_linter_tool/linters/tflint.py
terraform_linter_tool/linters/tfsec.py
terraform_linter_tool/models/__init__.py
terraform_linter_tool/models/checkov_model.py
terraform_linter_tool/models/tflint_model.py
terraform_linter_tool/models/tfsec_model.py
terraform_linter_tool/processor/__init__.py
terraform_linter_tool/processor/ai_processor.py
terraform_linter_tool/processor/checkov_processor.py
terraform_linter_tool/processor/lint_processor.py
terraform_linter_tool/processor/tflint_processor.py
terraform_linter_tool/processor/tfsec_processor.py
terraform_linter_tool/reporting/__init__.py
terraform_linter_tool/reporting/app_layout.py
terraform_linter_tool/reporting/assets/custom.css
terraform_linter_tool/reporting/assets/home-solid.svg
terraform_linter_tool/reporting/assets/home.svg
terraform_linter_tool/reporting/assets/logo.webp
terraform_linter_tool/reporting/base.py
terraform_linter_tool/reporting/bugfixes.txt
terraform_linter_tool/reporting/callbacks.py
terraform_linter_tool/reporting/dashboard.py
terraform_linter_tool/reporting/data_loader.py
terraform_linter_tool/resources/__init__.py
terraform_linter_tool/resources/config.yaml
terraform_linter_tool/utils/__init__.py
terraform_linter_tool/utils/config_utils.py
terraform_linter_tool/utils/file_utils.py
terraform_linter_tool/utils/linter_checker.py
terraform_linter_tool/utils/report_generator.py
terraform_linter_tool/utils/terraform_utils.py
infralint-0.2.7.dist-info/METADATA
infralint-0.2.7.dist-info/WHEEL
infralint-0.2.7.dist-info/entry_points.txt
infralint-0.2.7.dist-info/RECORD
